notifylibrary/__init__.py
notifylibrary/email_sender.py
notifylibrary/push_sender.py
notifylibrary/sms_sender.py
notifylib-0.0.2.dist-info/METADATA
notifylib-0.0.2.dist-info/WHEEL
notifylib-0.0.2.dist-info/top_level.txt
notifylib-0.0.2.dist-info/RECORD
