Metadata-Version: 2.1
Name: notifylib
Version: 0.0.2
Summary: notify users
Home-page: https://github.com/pypa/sampleproject
Author: Abinash
Author-email: abinashsp608@gmail.com
Classifier: Programming Language :: Python :: 3
Classifier: License :: OSI Approved :: MIT License
Classifier: Operating System :: OS Independent
Requires-Python: >=3.6
